ike/__init__.py
ike/const.py
ike/initiator.py
ike/payloads.py
ike/proposal.py
ike/protocol.py
ike/util/__init__.py
ike/util/cipher.py
ike/util/conv.py
ike/util/dh.py
ike/util/dump.py
ike/util/external.py
ike/util/prf.py
ike/util/pubkey.py
ike-0.1.1.dist-info/DESCRIPTION.rst
ike-0.1.1.dist-info/METADATA
ike-0.1.1.dist-info/RECORD
ike-0.1.1.dist-info/WHEEL
ike-0.1.1.dist-info/metadata.json
ike-0.1.1.dist-info/top_level.txt
