Metadata-Version: 2.0
Name: ike
Version: 0.1.1
Summary: Minimalistic Internet Key Exchange protocol v2 (RFC 5996) library
Home-page: http://github.com/kimvais/ike/
Author: Kimmo Parviainen-Jalanko
Author-email: k@77.fi
License: UNKNOWN
Download-URL: https://github.com/kimvais/ike/releases
Platform: UNKNOWN
Classifier: Development Status :: 3 - Alpha
Classifier: License :: OSI Approved :: MIT License
Classifier: Operating System :: Unix
Classifier: Programming Language :: Python :: 3.4
Classifier: Topic :: Communications
Classifier: Topic :: Internet
Classifier: Topic :: Security
Classifier: Topic :: Security :: Cryptography
Requires-Dist: rsa
Requires-Dist: cryptography
